odoo/addons/res_company_mastodon_link/README.rst
odoo/addons/res_company_mastodon_link/__init__.py
odoo/addons/res_company_mastodon_link/__manifest__.py
odoo/addons/res_company_mastodon_link/demo/demo_res_company.xml
odoo/addons/res_company_mastodon_link/i18n/fr.po
odoo/addons/res_company_mastodon_link/i18n/it.po
odoo/addons/res_company_mastodon_link/i18n/res_company_mastodon_link.pot
odoo/addons/res_company_mastodon_link/models/__init__.py
odoo/addons/res_company_mastodon_link/models/res_company.py
odoo/addons/res_company_mastodon_link/readme/CONTRIBUTORS.md
odoo/addons/res_company_mastodon_link/readme/DESCRIPTION.md
odoo/addons/res_company_mastodon_link/static/description/icon.png
odoo/addons/res_company_mastodon_link/static/description/index.html
odoo/addons/res_company_mastodon_link/static/description/res_company_form.png
odoo/addons/res_company_mastodon_link/views/view_res_company.xml
odoo_addon_res_company_mastodon_link-18.0.1.0.0.6.dist-info/METADATA
odoo_addon_res_company_mastodon_link-18.0.1.0.0.6.dist-info/WHEEL
odoo_addon_res_company_mastodon_link-18.0.1.0.0.6.dist-info/top_level.txt
odoo_addon_res_company_mastodon_link-18.0.1.0.0.6.dist-info/RECORD
